nanome_structure_prep/Settings.py
nanome_structure_prep/StructurePrep.py
nanome_structure_prep/__init__.py
nanome_structure_prep/assets/off.png
nanome_structure_prep/assets/on.png
nanome_structure_prep/json/Settings.json
nanome_structure_prep-0.2.6.dist-info/LICENSE
nanome_structure_prep-0.2.6.dist-info/METADATA
nanome_structure_prep-0.2.6.dist-info/WHEEL
nanome_structure_prep-0.2.6.dist-info/entry_points.txt
nanome_structure_prep-0.2.6.dist-info/top_level.txt
nanome_structure_prep-0.2.6.dist-info/RECORD
