Metadata-Version: 2.1
Name: nanome-structure-prep
Version: 0.2.6
Summary: A Nanome plugin to clean up selected structures.
Home-page: https://github.com/nanome-ai/plugin-structure-prep
Author: astrovicis
Author-email: max@nanome.ai
License: MIT
Keywords: virtual-reality,chemistry,python,api,plugin
Platform: any
Classifier: Development Status :: 3 - Alpha
Classifier: Intended Audience :: Science/Research
Classifier: Topic :: Scientific/Engineering :: Chemistry
Classifier: License :: OSI Approved :: MIT License
Classifier: Programming Language :: Python :: 2.7
Classifier: Programming Language :: Python :: 3.5
Classifier: Programming Language :: Python :: 3.6
Classifier: Programming Language :: Python :: 3.7
Requires-Dist: nanome
